<?xml version="1.0" encoding="utf-8"?>
<search>
  
  
  
  <entry>
    <title>Anson&#39;s First Post!!!</title>
    <link href="/first/"/>
    <url>/first/</url>
    
    <content type="html"><![CDATA[<p>Hello Everyone This is Anson</p><p>A student from China and I always welcome you come here and talk to me, but if you are not English speaker, you can chose to visit my <a href="https://anson.fun/">Chinese home page</a>.<br>But I give English speaker another platform based on telegram <a href="https://t.me/AnsonsChannelEN">join</a> and this is my first blog, if have any wrong from my website, welcome you email me in about page</p>]]></content>
    
    
    
    <tags>
      
      <tag>post</tag>
      
    </tags>
    
  </entry>
  
  
  
  
</search>
